errorcalc/__init__.py
errorcalc-0.0.1.dist-info/LICENSE. txt
errorcalc-0.0.1.dist-info/METADATA
errorcalc-0.0.1.dist-info/WHEEL
errorcalc-0.0.1.dist-info/top_level.txt
errorcalc-0.0.1.dist-info/RECORD
